<?xml version="1.0" encoding="UTF-8"?>
<scores><udd><score>1</score><wrong>2</wrong></udd><uguest><score>6</score><wrong>6</wrong></uguest><udjjahdjh><score>2</score><wrong>2</wrong></udjjahdjh><uddd><score>1</score><wrong>1</wrong></uddd><uajd><score>1</score><wrong>1</wrong></uajd><umjbbs><score>1</score><wrong>1</wrong></umjbbs><uabfbm><score>1</score><wrong>1</wrong></uabfbm><udamnfbam><score>1</score><wrong>1</wrong></udamnfbam><udand_dnab><score>1</score><wrong>1</wrong></udand_dnab><udgadda><score>1</score><wrong>1</wrong></udgadda></scores>
